[
  {
    "name": "(미상)",
    "lat": 37.36673,
    "lng": 129.09538,
    "trees": 22617,
    "length": 0,
    "gu": "기장군",
    "species": [
      {
        "name": "벚나무",
        "count": 5457
      },
      {
        "name": "미분류",
        "count": 4588
      },
      {
        "name": "이팝나무",
        "count": 3943
      },
      {
        "name": "은행나무",
        "count": 2430
      },
      {
        "name": "느티나무",
        "count": 2393
      },
      {
        "name": "기타",
        "count": 1350
      },
      {
        "name": "기타상록",
        "count": 1027
      },
      {
        "name": "기타낙엽",
        "count": 901
      },
      {
        "name": "버즘나무",
        "count": 361
      },
      {
        "name": "해송",
        "count": 97
      },
      {
        "name": "후박나무",
        "count": 70
      }
    ]
  },
  {
    "name": "모전길",
    "lat": 35.1982701,
    "lng": 126.8090505,
    "trees": 207,
    "length": 0,
    "gu": "기장군",
    "species": [
      {
        "name": "느티나무",
        "count": 207
      }
    ]
  },
  {
    "name": "산단로",
    "lat": 35.1982701,
    "lng": 126.8090505,
    "trees": 785,
    "length": 0,
    "gu": "기장군",
    "species": [
      {
        "name": "기타낙엽",
        "count": 785
      }
    ]
  },
  {
    "name": "방곡길",
    "lat": 35.1982701,
    "lng": 126.8090505,
    "trees": 183,
    "length": 0,
    "gu": "기장군",
    "species": [
      {
        "name": "이팝나무",
        "count": 183
      }
    ]
  },
  {
    "name": "산단4길",
    "lat": 35.1982701,
    "lng": 126.8090505,
    "trees": 84,
    "length": 0,
    "gu": "기장군",
    "species": [
      {
        "name": "기타낙엽",
        "count": 84
      }
    ]
  },
  {
    "name": "가노선",
    "lat": 35.1982701,
    "lng": 126.8090505,
    "trees": 1407,
    "length": 0,
    "gu": "기장군",
    "species": [
      {
        "name": "이팝나무",
        "count": 542
      },
      {
        "name": "느티나무",
        "count": 410
      },
      {
        "name": "기타상록",
        "count": 247
      },
      {
        "name": "기타낙엽",
        "count": 206
      },
      {
        "name": "벚나무",
        "count": 2
      }
    ]
  },
  {
    "name": "읍내1길",
    "lat": 35.24,
    "lng": 129.22,
    "trees": 79,
    "length": 0,
    "gu": "기장군",
    "species": [
      {
        "name": "벚나무",
        "count": 79
      }
    ]
  },
  {
    "name": "대변로",
    "lat": 35.2255523,
    "lng": 129.228382,
    "trees": 249,
    "length": 0,
    "gu": "기장군",
    "species": [
      {
        "name": "벚나무",
        "count": 229
      },
      {
        "name": "해송",
        "count": 12
      },
      {
        "name": "기타상록",
        "count": 5
      },
      {
        "name": "미분류",
        "count": 2
      },
      {
        "name": "결식지",
        "count": 1
      }
    ]
  },
  {
    "name": "곰내길",
    "lat": 35.3058654,
    "lng": 129.172041,
    "trees": 20,
    "length": 0,
    "gu": "기장군",
    "species": [
      {
        "name": "기타상록",
        "count": 13
      },
      {
        "name": "벚나무",
        "count": 7
      }
    ]
  },
  {
    "name": "장안로",
    "lat": 35.3576802,
    "lng": 129.2505164,
    "trees": 664,
    "length": 0,
    "gu": "기장군",
    "species": [
      {
        "name": "벚나무",
        "count": 662
      },
      {
        "name": "결식지",
        "count": 2
      }
    ]
  },
  {
    "name": "안평길",
    "lat": 35.24,
    "lng": 129.22,
    "trees": 13,
    "length": 0,
    "gu": "기장군",
    "species": [
      {
        "name": "벚나무",
        "count": 13
      }
    ]
  },
  {
    "name": "갑골길",
    "lat": 35.24,
    "lng": 129.22,
    "trees": 12,
    "length": 0,
    "gu": "기장군",
    "species": [
      {
        "name": "미분류",
        "count": 12
      }
    ]
  },
  {
    "name": "좌동로,해운로, 기장대로",
    "lat": 8.0783857,
    "lng": 98.9004066,
    "trees": 952,
    "length": 0,
    "gu": "기장군",
    "species": [
      {
        "name": "미분류",
        "count": 567
      },
      {
        "name": "벚나무",
        "count": 323
      },
      {
        "name": "이팝나무",
        "count": 41
      },
      {
        "name": "후박나무",
        "count": 21
      }
    ]
  },
  {
    "name": "죽성길",
    "lat": 35.24,
    "lng": 129.22,
    "trees": 158,
    "length": 0,
    "gu": "기장군",
    "species": [
      {
        "name": "미분류",
        "count": 158
      }
    ]
  },
  {
    "name": "기장해안로",
    "lat": 35.1996433,
    "lng": 129.2240272,
    "trees": 265,
    "length": 0,
    "gu": "기장군",
    "species": [
      {
        "name": "미분류",
        "count": 265
      }
    ]
  },
  {
    "name": "산성길",
    "lat": 35.24,
    "lng": 129.22,
    "trees": 53,
    "length": 0,
    "gu": "기장군",
    "species": [
      {
        "name": "미분류",
        "count": 53
      }
    ]
  },
  {
    "name": "기장시장길",
    "lat": 35.24,
    "lng": 129.22,
    "trees": 74,
    "length": 0,
    "gu": "기장군",
    "species": [
      {
        "name": "미분류",
        "count": 74
      }
    ]
  },
  {
    "name": "대라길",
    "lat": 35.24,
    "lng": 129.22,
    "trees": 65,
    "length": 0,
    "gu": "기장군",
    "species": [
      {
        "name": "미분류",
        "count": 65
      }
    ]
  },
  {
    "name": "덕발길",
    "lat": 35.24,
    "lng": 129.22,
    "trees": 16,
    "length": 0,
    "gu": "기장군",
    "species": [
      {
        "name": "미분류",
        "count": 16
      }
    ]
  },
  {
    "name": "기장중앙로",
    "lat": 35.2472852,
    "lng": 129.213778,
    "trees": 183,
    "length": 0,
    "gu": "기장군",
    "species": [
      {
        "name": "은행나무",
        "count": 93
      },
      {
        "name": "벚나무",
        "count": 45
      },
      {
        "name": "미분류",
        "count": 44
      },
      {
        "name": "해송",
        "count": 1
      }
    ]
  },
  {
    "name": "대청6길",
    "lat": 35.24,
    "lng": 129.22,
    "trees": 20,
    "length": 0,
    "gu": "기장군",
    "species": [
      {
        "name": "미분류",
        "count": 20
      }
    ]
  },
  {
    "name": "반룡로",
    "lat": 35.3510685,
    "lng": 129.2562692,
    "trees": 13,
    "length": 0,
    "gu": "기장군",
    "species": [
      {
        "name": "벚나무",
        "count": 13
      }
    ]
  },
  {
    "name": "임랑해안길",
    "lat": 35.3188708,
    "lng": 129.2637073,
    "trees": 1,
    "length": 0,
    "gu": "기장군",
    "species": [
      {
        "name": "미분류",
        "count": 1
      }
    ]
  },
  {
    "name": "정관남로",
    "lat": 35.1982701,
    "lng": 126.8090505,
    "trees": 1302,
    "length": 0,
    "gu": "기장군",
    "species": [
      {
        "name": "이팝나무",
        "count": 1139
      },
      {
        "name": "기타낙엽",
        "count": 163
      }
    ]
  },
  {
    "name": "정관7길",
    "lat": 35.1982701,
    "lng": 126.8090505,
    "trees": 79,
    "length": 0,
    "gu": "기장군",
    "species": [
      {
        "name": "느티나무",
        "count": 79
      }
    ]
  },
  {
    "name": "용수길",
    "lat": 35.1982701,
    "lng": 126.8090505,
    "trees": 168,
    "length": 0,
    "gu": "기장군",
    "species": [
      {
        "name": "기타상록",
        "count": 94
      },
      {
        "name": "느티나무",
        "count": 74
      }
    ]
  },
  {
    "name": "정관중앙로",
    "lat": 35.1982701,
    "lng": 126.8090505,
    "trees": 300,
    "length": 0,
    "gu": "기장군",
    "species": [
      {
        "name": "느티나무",
        "count": 159
      },
      {
        "name": "벚나무",
        "count": 141
      }
    ]
  },
  {
    "name": "정관5길",
    "lat": 35.1982701,
    "lng": 126.8090505,
    "trees": 269,
    "length": 0,
    "gu": "기장군",
    "species": [
      {
        "name": "느티나무",
        "count": 185
      },
      {
        "name": "기타상록",
        "count": 84
      }
    ]
  },
  {
    "name": "정관3길",
    "lat": 35.1982701,
    "lng": 126.8090505,
    "trees": 157,
    "length": 0,
    "gu": "기장군",
    "species": [
      {
        "name": "기타상록",
        "count": 156
      },
      {
        "name": "느티나무",
        "count": 1
      }
    ]
  },
  {
    "name": "가동길",
    "lat": 35.1982701,
    "lng": 126.8090505,
    "trees": 56,
    "length": 0,
    "gu": "기장군",
    "species": [
      {
        "name": "느티나무",
        "count": 56
      }
    ]
  },
  {
    "name": "가동3길",
    "lat": 35.1982701,
    "lng": 126.8090505,
    "trees": 51,
    "length": 0,
    "gu": "기장군",
    "species": [
      {
        "name": "느티나무",
        "count": 51
      }
    ]
  },
  {
    "name": "정관6길",
    "lat": 35.1982701,
    "lng": 126.8090505,
    "trees": 159,
    "length": 0,
    "gu": "기장군",
    "species": [
      {
        "name": "기타상록",
        "count": 106
      },
      {
        "name": "이팝나무",
        "count": 53
      }
    ]
  },
  {
    "name": "정관덕산길",
    "lat": 35.1982701,
    "lng": 126.8090505,
    "trees": 162,
    "length": 0,
    "gu": "기장군",
    "species": [
      {
        "name": "기타상록",
        "count": 109
      },
      {
        "name": "느티나무",
        "count": 51
      },
      {
        "name": "미분류",
        "count": 2
      }
    ]
  },
  {
    "name": "용수공단2길",
    "lat": 35.1982701,
    "lng": 126.8090505,
    "trees": 39,
    "length": 0,
    "gu": "기장군",
    "species": [
      {
        "name": "기타낙엽",
        "count": 39
      }
    ]
  },
  {
    "name": "산단2길",
    "lat": 35.1982701,
    "lng": 126.8090505,
    "trees": 48,
    "length": 0,
    "gu": "기장군",
    "species": [
      {
        "name": "이팝나무",
        "count": 48
      }
    ]
  },
  {
    "name": "구연길",
    "lat": 35.1982701,
    "lng": 126.8090505,
    "trees": 101,
    "length": 0,
    "gu": "기장군",
    "species": [
      {
        "name": "기타상록",
        "count": 101
      }
    ]
  },
  {
    "name": "정관1길",
    "lat": 35.1982701,
    "lng": 126.8090505,
    "trees": 159,
    "length": 0,
    "gu": "기장군",
    "species": [
      {
        "name": "느티나무",
        "count": 159
      }
    ]
  },
  {
    "name": "정관2길",
    "lat": 35.1982701,
    "lng": 126.8090505,
    "trees": 170,
    "length": 0,
    "gu": "기장군",
    "species": [
      {
        "name": "기타상록",
        "count": 170
      }
    ]
  },
  {
    "name": "정관8길",
    "lat": 35.1982701,
    "lng": 126.8090505,
    "trees": 59,
    "length": 0,
    "gu": "기장군",
    "species": [
      {
        "name": "느티나무",
        "count": 59
      }
    ]
  },
  {
    "name": "구연방곡길",
    "lat": 35.1982701,
    "lng": 126.8090505,
    "trees": 307,
    "length": 0,
    "gu": "기장군",
    "species": [
      {
        "name": "기타낙엽",
        "count": 307
      }
    ]
  },
  {
    "name": "산단6길",
    "lat": 35.1982701,
    "lng": 126.8090505,
    "trees": 73,
    "length": 0,
    "gu": "기장군",
    "species": [
      {
        "name": "기타상록",
        "count": 73
      }
    ]
  },
  {
    "name": "정관4길",
    "lat": 35.1982701,
    "lng": 126.8090505,
    "trees": 166,
    "length": 0,
    "gu": "기장군",
    "species": [
      {
        "name": "기타상록",
        "count": 166
      }
    ]
  },
  {
    "name": "방곡1길",
    "lat": 35.1982701,
    "lng": 126.8090505,
    "trees": 71,
    "length": 0,
    "gu": "기장군",
    "species": [
      {
        "name": "이팝나무",
        "count": 71
      }
    ]
  },
  {
    "name": "방곡3길",
    "lat": 35.1982701,
    "lng": 126.8090505,
    "trees": 42,
    "length": 0,
    "gu": "기장군",
    "species": [
      {
        "name": "벚나무",
        "count": 42
      }
    ]
  },
  {
    "name": "모전1길",
    "lat": 35.1982701,
    "lng": 126.8090505,
    "trees": 76,
    "length": 0,
    "gu": "기장군",
    "species": [
      {
        "name": "이팝나무",
        "count": 76
      }
    ]
  },
  {
    "name": "구연3길",
    "lat": 35.1982701,
    "lng": 126.8090505,
    "trees": 62,
    "length": 0,
    "gu": "기장군",
    "species": [
      {
        "name": "이팝나무",
        "count": 61
      },
      {
        "name": "기타상록",
        "count": 1
      }
    ]
  },
  {
    "name": "구연4길",
    "lat": 35.1982701,
    "lng": 126.8090505,
    "trees": 42,
    "length": 0,
    "gu": "기장군",
    "species": [
      {
        "name": "이팝나무",
        "count": 42
      }
    ]
  },
  {
    "name": "양수1길",
    "lat": 35.1982701,
    "lng": 126.8090505,
    "trees": 40,
    "length": 0,
    "gu": "기장군",
    "species": [
      {
        "name": "기타낙엽",
        "count": 40
      }
    ]
  },
  {
    "name": "정관상곡2길",
    "lat": 35.1982701,
    "lng": 126.8090505,
    "trees": 23,
    "length": 0,
    "gu": "기장군",
    "species": [
      {
        "name": "기타낙엽",
        "count": 23
      }
    ]
  },
  {
    "name": "철마로",
    "lat": 35.257507,
    "lng": 129.1741835,
    "trees": 62,
    "length": 0,
    "gu": "기장군",
    "species": [
      {
        "name": "벚나무",
        "count": 62
      }
    ]
  },
  {
    "name": "반송로",
    "lat": 35.2517835,
    "lng": 129.2070201,
    "trees": 89,
    "length": 0,
    "gu": "기장군",
    "species": [
      {
        "name": "은행나무",
        "count": 63
      },
      {
        "name": "벚나무",
        "count": 19
      },
      {
        "name": "기타상록",
        "count": 5
      },
      {
        "name": "결식지",
        "count": 2
      }
    ]
  },
  {
    "name": "구연2길",
    "lat": 35.1982701,
    "lng": 126.8090505,
    "trees": 7,
    "length": 0,
    "gu": "기장군",
    "species": [
      {
        "name": "이팝나무",
        "count": 7
      }
    ]
  },
  {
    "name": "협동길",
    "lat": 35.24,
    "lng": 129.22,
    "trees": 69,
    "length": 0,
    "gu": "기장군",
    "species": [
      {
        "name": "이팝나무",
        "count": 69
      }
    ]
  },
  {
    "name": "가동옛길",
    "lat": 35.3314338,
    "lng": 129.1798077,
    "trees": 49,
    "length": 0,
    "gu": "기장군",
    "species": [
      {
        "name": "이팝나무",
        "count": 49
      }
    ]
  },
  {
    "name": "고촌길",
    "lat": 35.24,
    "lng": 129.22,
    "trees": 115,
    "length": 0,
    "gu": "기장군",
    "species": [
      {
        "name": "이팝나무",
        "count": 104
      },
      {
        "name": "후박나무",
        "count": 11
      }
    ]
  },
  {
    "name": "내리길",
    "lat": 35.2159899,
    "lng": 129.1946867,
    "trees": 118,
    "length": 0,
    "gu": "기장군",
    "species": [
      {
        "name": "벚나무",
        "count": 117
      },
      {
        "name": "기타상록",
        "count": 1
      }
    ]
  },
  {
    "name": "동부길",
    "lat": 35.24,
    "lng": 129.22,
    "trees": 1,
    "length": 0,
    "gu": "기장군",
    "species": [
      {
        "name": "기타낙엽",
        "count": 1
      }
    ]
  }
]